PythonDSSAnalysis/DSSHandler.py
PythonDSSAnalysis/__init__.py
PythonDSSAnalysis/sampleRun.py
PythonDSSAnalysis/sampledata.csv
PythonDSSAnalysis/samplemodel.yml
PythonDSSAnalysis/samplemodelexp.yml
pythondssanalysis-1.3.2.dist-info/METADATA
pythondssanalysis-1.3.2.dist-info/WHEEL
pythondssanalysis-1.3.2.dist-info/licenses/LICENSE
pythondssanalysis-1.3.2.dist-info/RECORD
