Metadata-Version: 2.4
Name: PythonDSSAnalysis
Version: 1.3.2
Author-email: Grant Hendrickson <granthendrickson19@gmail.com>
License-File: LICENSE
Classifier: License :: OSI Approved :: MIT License
Classifier: Operating System :: OS Independent
Classifier: Programming Language :: Python :: 3
Requires-Python: >=3.9
Requires-Dist: numpy>=2.0
